openepub/__init__.py
openepub/common.py
openepub/exceptions.py
openepub/epub/epub.py
openepub/epub/item.py
openepub/epub/package.py
openepub-0.0.9.dist-info/METADATA
openepub-0.0.9.dist-info/WHEEL
openepub-0.0.9.dist-info/licenses/LICENSE
openepub-0.0.9.dist-info/RECORD
